SNMatrices/__init__.py
SNMatrices/operations.py
SNMatrices-0.3.dist-info/License.txt
SNMatrices-0.3.dist-info/METADATA
SNMatrices-0.3.dist-info/WHEEL
SNMatrices-0.3.dist-info/top_level.txt
SNMatrices-0.3.dist-info/RECORD
