Metadata-Version: 2.1
Name: SNMatrices
Version: 0.3
Summary: Basic Operations For Matrices
Author-email: Shanmuga Nathan V <Shanmu2224@gmail.com>
Project-URL: Homepage, https://github.com/pypa/sampleproject
Project-URL: Bug Tracker, https://github.com/pypa/sampleproject/issues
Classifier: Programming Language :: Python :: 3
Classifier: License :: OSI Approved :: MIT License
Classifier: Operating System :: OS Independent
Requires-Python: >=3.7
License-File: License.txt
